posto_sdk/__init__.py
posto_sdk/api_utils.py
posto_sdk/channel_manager.py
posto_sdk/network_settings.py
posto_sdk/posto_sdk.py
posto_sdk/schedule_manager.py
posto_sdk/social_media_manager.py
posto_sdk-3.0.5.dist-info/METADATA
posto_sdk-3.0.5.dist-info/WHEEL
posto_sdk-3.0.5.dist-info/top_level.txt
posto_sdk-3.0.5.dist-info/RECORD
